{
  "schemaVersion": 1,
  "contractRevision": "1",
  "authority": {
    "repository": "Fortemi/fortemi",
    "producerCommit": "Use the immutable Git commit containing this receipt."
  },
  "knowledgeShard": {
    "format": "matric-shard",
    "schemaVersion": "1.0.0",
    "minimumReaderVersion": "1.0.0"
  },
  "profiles": {
    "core-v1": {
      "supported": true,
      "schemaRoot": "contracts/knowledge-shard/1.0.0/core-v1",
      "components": ["notes", "collections", "tags", "templates", "links"]
    },
    "full-v1": {
      "supported": false,
      "status": "reserved"
    },
    "record-v1": {
      "supported": false,
      "status": "reserved"
    }
  },
  "schemaBundle": {
    "aggregateAlgorithm": "sha256(raw file bytes concatenated in lexicographic path order)",
    "sha256": "2520ba0b3a8a020f5c540e88fd31233c7ddbe0d343d1e6a884ed689c8e1d3710",
    "files": {
      "contracts/knowledge-shard/1.0.0/core-v1/collection.schema.json": "af4bd6b0acaf79d7f750c24ee3eb049efaff154f31bd2c17dd10b2b5aa949af4",
      "contracts/knowledge-shard/1.0.0/core-v1/link.schema.json": "dc9d610944c515d96012f4c4151ac7d2e001d72b2eb134c26a8fcf02a81cfd64",
      "contracts/knowledge-shard/1.0.0/core-v1/manifest.schema.json": "65a6cf021d2fb3f167aab54253f54e1ea9f649f37bbc5944449a9cc456e4ee47",
      "contracts/knowledge-shard/1.0.0/core-v1/note.schema.json": "e89728c7d722956b32ebc35cda70190398758bb00d6d7832bdc3da3d36d3db3f",
      "contracts/knowledge-shard/1.0.0/core-v1/tag.schema.json": "18e59bc020ca2f4304dd6bd9dc5d2e8fd082b677d745f4f1b742ff0ccf9af01d",
      "contracts/knowledge-shard/1.0.0/core-v1/template.schema.json": "5504829dcf4053d573b359b355885757ab053553b9be39a0930b02fb235dde59"
    }
  },
  "goldenCorpus": {
    "root": "tests/fixtures/shards/core-v1-valid",
    "aggregateAlgorithm": "sha256(raw file bytes concatenated in lexicographic path order)",
    "sha256": "7e8c529b7f5ac404d27302499c74470e137b03d27fce54111acf8989b1147ae1"
  },
  "limitations": [
    "core-v1 attachment records are metadata/reference projections; attachment bytes are not included",
    "full-v1 and record-v1 are reserved and are not supported by this release",
    "this receipt does not establish atomic clean-database semantic roundtrip conformance"
  ]
}
